{
  "provider_id": "7290873255550",
  "provider_name": "טיב טעם",
  "branches": {
    "002": {
      "name": "נתניה",
      "address": "בני גאון 2",
      "city": "7400"
    },
    "003": {
      "name": "אשדוד",
      "address": "ז'בוטינסקי 45 מתחם סטאר סנטר",
      "city": "70"
    },
    "006": {
      "name": "בת ים",
      "address": "אהוד קינמון 14",
      "city": "6200"
    },
    "007": {
      "name": "אשקלון",
      "address": "התחיה 1",
      "city": "7100"
    },
    "010": {
      "name": "כרמיאל",
      "address": "מעלה כמון 3 מתחם ביג",
      "city": "1139"
    },
    "012": {
      "name": "חוצות המפרץ (קריות)",
      "address": "החרושת 10 מתחם חוצות המפרץ",
      "city": "4000"
    },
    "014": {
      "name": "ראשון מזרח",
      "address": "המכבים 62 צומת בית דגן",
      "city": "8300"
    },
    "015": {
      "name": "באר שבע חדש",
      "address": "יצחק נפחא 25 מתחם מבנה",
      "city": "9000"
    },
    "017": {
      "name": "מודיעין ישפרו",
      "address": "שדרות המלאכות 12",
      "city": "1200"
    },
    "018": {
      "name": "רחובות",
      "address": "אופנהימר 2",
      "city": "8400"
    },
    "019": {
      "name": "רמת החייל",
      "address": "דבורה הנביאה 122",
      "city": "5000"
    },
    "020": {
      "name": "חולון עזריאלי",
      "address": "הרוקמים 26",
      "city": "6600"
    },
    "021": {
      "name": "יהוד",
      "address": "אלטלף 1",
      "city": "9400"
    },
    "022": {
      "name": "קניון דרורים",
      "address": "קניון דרורים",
      "city": "386"
    },
    "023": {
      "name": "קיסריה",
      "address": "דולב 14",
      "city": "1167"
    },
    "024": {
      "name": "הוד השרון",
      "address": "סוקולוב 46 כיכר המושבה",
      "city": "9700"
    },
    "025": {
      "name": "צומת סביון",
      "address": "השדרה האקדמית 4 בקעת אונו",
      "city": "587"
    },
    "030": {
      "name": "מפגש מזרע",
      "address": "קיבוץ מזרע",
      "city": "104"
    },
    "051": {
      "name": "דלי רעננה",
      "address": "אחוזה 269 פארק מול",
      "city": "8700"
    },
    "052": {
      "name": "הרצליה",
      "address": "בן גוריון 56 פינת בר כוכבא",
      "city": "6400"
    },
    "054": {
      "name": "בן-יהודה 1",
      "address": "בן יהודה 1",
      "city": "5000"
    },
    "056": {
      "name": "טופ דן",
      "address": "פנחס רוזן 72",
      "city": "5000"
    },
    "057": {
      "name": "מאז\"ה",
      "address": "מאז\"ה 40",
      "city": "5000"
    },
    "058": {
      "name": "בן-יהודה 130",
      "address": "בן יהודה 130 פינת בן גוריון",
      "city": "5000"
    },
    "059": {
      "name": "בן יהודה 181",
      "address": "בן יהודה 181",
      "city": "5000"
    },
    "061": {
      "name": "חשמונאים 91",
      "address": "חשמונאים 91",
      "city": "5000"
    },
    "063": {
      "name": "אבן גבירול 64",
      "address": "אבן גבירול 64",
      "city": "5000"
    },
    "068": {
      "name": "סירקין 13",
      "address": "סירקין 13",
      "city": "6300"
    },
    "070": {
      "name": "יפו",
      "address": "שדרות ירושלים 4",
      "city": "5000"
    },
    "071": {
      "name": "פרישמן",
      "address": "פרישמן 13",
      "city": "5000"
    },
    "073": {
      "name": "פנקס 2",
      "address": "אבן גבירול 164",
      "city": "5000"
    },
    "074": {
      "name": "ארלוזורוב",
      "address": "ארלוזורוב 149",
      "city": "5000"
    },
    "075": {
      "name": "יהודה מכבי",
      "address": "יהודה מכבי 69",
      "city": "5000"
    },
    "079": {
      "name": "חולון סיטי קוגל",
      "address": "שדרות לוי אשכול 30",
      "city": "6600"
    },
    "080": {
      "name": "יגאל אלון דלי",
      "address": "יגאל אלון 94",
      "city": "5000"
    },
    "082": {
      "name": "דלי כורזין גבעתיים",
      "address": "תפוצות ישראל 6",
      "city": "6300"
    },
    "083": {
      "name": "מרכז כיתן",
      "address": "פנחס רוזן 67",
      "city": "5000"
    },
    "084": {
      "name": "דלי איינשטיין",
      "address": "איינשטיין 10",
      "city": "5000"
    },
    "085": {
      "name": "בית הדובדבן - אונו",
      "address": "הדובדבן 7",
      "city": "2620"
    },
    "087": {
      "name": "מונטיפיורי פתח תקוה",
      "address": "רוטישילד 57",
      "city": "7900"
    },
    "088": {
      "name": "רמת אפעל",
      "address": "דרך שיבא 16",
      "city": "8600"
    },
    "089": {
      "name": "קינג גורג",
      "address": "קינג גורג 8",
      "city": "5000"
    },
    "091": {
      "name": "המסגר",
      "address": "המסגר 37",
      "city": "5000"
    },
    "092": {
      "name": "מחניים",
      "address": "מחניים 4",
      "city": "4000"
    },
    "094": {
      "name": "קרית מוצקין",
      "address": "ש\"י עגנון 16",
      "city": "8200"
    },
    "156": {
      "name": "עדן גן העיר",
      "address": "אבן גבירול 71",
      "city": "5000"
    },
    "502": {
      "name": "ליקוט נתניה",
      "address": "",
      "city": "7400"
    },
    "503": {
      "name": "ליקוט טיב טעם אשדוד",
      "address": "",
      "city": "70"
    },
    "512": {
      "name": "ליקוט טיב טעם קריות",
      "address": "",
      "city": "4000"
    },
    "514": {
      "name": "ליקוט ראשון מזרח",
      "address": "",
      "city": "8300"
    },
    "515": {
      "name": "ליקוט טיב באר שבע",
      "address": "",
      "city": "9000"
    },
    "519": {
      "name": "ליקוט רמת החייל",
      "address": "",
      "city": "5000"
    },
    "523": {
      "name": "ליקוט קיסריה",
      "address": "",
      "city": "1167"
    }
  }
}